mux2/mux2.v
module mux2 (
    input a,
    input b,
    input sel,
    output y
);

assign y = sel? a:b;

endmodule

mux2/mux2_tb.v
`timescale 1ns / 1ps
`include "mux2.v"
module mux2_tb;

    // Declare testbench signals
    reg a;
    reg b;
    reg sel;
    wire y;

    // Instantiate or gate module
    mux2 dut (
        .a(a),
        .b(b),
        .sel(sel),
        .y(y)
    );

    // Stimulus block
    initial begin

       $display("Time\tSel\tA\tB\tY");
       $monitor("%0dns\t%b\t%b\t%b\t%b", $time, sel, a, b, y);

        // Apply all input combinations
        a = 0; b = 0; sel = 0; #10;
        a = 0; b = 1; sel = 0; #10;
        a = 1; b = 0; sel = 0; #10;
        a = 1; b = 1; sel = 0; #10;

        a = 0; b = 0; sel = 1; #10;
        a = 0; b = 1; sel = 1; #10;
        a = 1; b = 0; sel = 1; #10;
        a = 1; b = 1; sel = 1; #10;
        $finish;
    end
    
initial begin
    $dumpfile("mux2.vcd");
    $dumpvars(0, mux2_tb);
end
endmodule

mux2/mux2.vcd
$date
	Fri May 23 08:12:03 2025
$end
$version
	Icarus Verilog
$end
$timescale
	1ps
$end
$scope module mux2_tb $end
$var wire 1 ! y $end
$var reg 1 " a $end
$var reg 1 # b $end
$var reg 1 $ sel $end
$scope module dut $end
$var wire 1 " a $end
$var wire 1 # b $end
$var wire 1 $ sel $end
$var wire 1 ! y $end
$upscope $end
$upscope $end
$enddefinitions $end
$comment Show the parameter values. $end
$dumpall
$end
#0
$dumpvars
0$
0#
0"
0!
$end
#10000
1!
1#
#20000
0!
0#
1"
#30000
1!
1#
#40000
0!
1$
0#
0"
#50000
1#
#60000
1!
0#
1"
#70000
1#
