full_adder/full_adder.v
module full_adder(
    input wire a,
    input wire b,
    input wire cin,
    output wire sum,
    output wire cout
);

assign sum = a^b^cin;
assign cout = a&b | a&cin | b&cin;

endmodule

full_adder/full_adder_tb.v
`timescale 1ns / 1ps
`include "full_adder.v"
module full_adder_tb;

    // Declare testbench signals
    reg a;
    reg b;
    reg cin;
    wire cout;
    wire sum;

    // Instantiate and gate module
    full_adder dut (
        .a(a),
        .b(b),
        .sum(sum),
        .cin(cin),
        .cout(cout)
    );

    // Stimulus
    initial begin
        $display("Time | a   b   cin  |   cout   sum");
        $display("--------------------------");

        a = 0; b = 0; cin = 0; #10;
        $display("%4t | %b   %b   %b  |  %b    %b", $time, a, b, cin, cout, sum);

        a = 0; b = 0; cin = 1; #10;
        $display("%4t | %b   %b   %b  |  %b    %b", $time, a, b, cin, cout, sum);

        a = 0; b = 1; cin = 0; #10;
        $display("%4t | %b   %b   %b  |  %b    %b", $time, a, b, cin, cout, sum);
 
        a = 0; b = 1; cin = 1; #10;
        $display("%4t | %b   %b   %b  |  %b    %b", $time, a, b, cin, cout, sum);

        a = 1; b = 0; cin = 0; #10;
        $display("%4t | %b   %b   %b  |  %b    %b", $time, a, b, cin, cout, sum);

        a = 1; b = 0; cin = 1; #10;
        $display("%4t | %b   %b   %b  |  %b    %b", $time, a, b, cin, cout, sum);

        a = 1; b = 1; cin = 0; #10;
        $display("%4t | %b   %b   %b  |  %b    %b", $time, a, b, cin, cout, sum);

        a = 1; b = 1; cin = 1; #10;
        $display("%4t | %b   %b   %b  |  %b    %b", $time, a, b, cin, cout, sum);

        $finish;
    end

    // For waveform generation
    initial begin
        $dumpfile("full_adder.vcd");
        $dumpvars(0, full_adder_tb);
    end

endmodule

full_adder/full_adder.vcd
$date
	Thu May 22 12:18:22 2025
$end
$version
	Icarus Verilog
$end
$timescale
	1ps
$end
$scope module full_adder_tb $end
$var wire 1 ! sum $end
$var wire 1 " cout $end
$var reg 1 # a $end
$var reg 1 $ b $end
$var reg 1 % cin $end
$scope module dut $end
$var wire 1 # a $end
$var wire 1 $ b $end
$var wire 1 % cin $end
$var wire 1 " cout $end
$var wire 1 ! sum $end
$upscope $end
$upscope $end
$enddefinitions $end
$comment Show the parameter values. $end
$dumpall
$end
#0
$dumpvars
0%
0$
0#
0"
0!
$end
#10000
1!
1%
#20000
0%
1$
#30000
1"
0!
1%
#40000
0"
1!
0%
0$
1#
#50000
1"
0!
1%
#60000
0%
1$
#70000
1!
1%
